BBGDataUtils/BBGDataUtils.py
BBGDataUtils/__init__.py
BBGDataUtils/plot_utilities.py
BBGDataUtils/plot_voltron.py
BBGDataUtils-0.0.3.dist-info/LICENSE
BBGDataUtils-0.0.3.dist-info/METADATA
BBGDataUtils-0.0.3.dist-info/WHEEL
BBGDataUtils-0.0.3.dist-info/top_level.txt
BBGDataUtils-0.0.3.dist-info/RECORD
