Metadata-Version: 2.1
Name: BBGDataUtils
Version: 0.0.3
Summary: Utility for extracting BBG timeseries data into Pandas objects w/ caching
Home-page: https://github.com/pypa/sampleproject
Author: T. Nicolas Steinbach
Author-email: t@steinbachs.us
License: UNKNOWN
Project-URL: Bug Tracker, https://github.com/pypa/sampleproject/issues
Platform: UNKNOWN
Classifier: Programming Language :: Python :: 3
Classifier: License :: OSI Approved :: MIT License
Classifier: Operating System :: Microsoft :: Windows :: Windows 10
Requires-Python: >=3.6
License-File: LICENSE
